README.rst
setup.py
flask_validate_json/__init__.py
flask_validate_json/custom_message.py
flask_validate_json/default_fill.py
flask_validate_json/validatejson.py
flask_validate_json.egg-info/PKG-INFO
flask_validate_json.egg-info/SOURCES.txt
flask_validate_json.egg-info/dependency_links.txt
flask_validate_json.egg-info/requires.txt
flask_validate_json.egg-info/top_level.txt