Metadata-Version: 1.1
Name: flask-validate-json
Version: 0.0.1
Summary: This is a Flask Plugin to be used for Validate JSON request data.
Home-page: https://github.com/machine-w/flask-validate-json
Author: machine-w
Author-email: steve2008.ma@gmail.com
License: MIT
Keywords: flask,json,validation,schema,jsonschema
Platform: UNKNOWN
Classifier: Framework :: Flask
Classifier: License :: OSI Approved :: MIT License
Classifier: Programming Language :: Python :: 2.7
Classifier: Programming Language :: Python :: 3.4
Classifier: Programming Language :: Python :: 3.5
Classifier: Programming Language :: Python :: 3.6
Classifier: Programming Language :: Python :: 3.7
